neolith/__init__.py
neolith/protocol/__init__.py
neolith/protocol/base.py
neolith-0.0.1.dist-info/LICENSE
neolith-0.0.1.dist-info/METADATA
neolith-0.0.1.dist-info/WHEEL
neolith-0.0.1.dist-info/top_level.txt
neolith-0.0.1.dist-info/RECORD
